logo_diagram_generator/__init__.py
logo_diagram_generator/cli.py
logo_diagram_generator/download_logos.py
logo_diagram_generator/generate_diagram.py
logo_diagram_generator/utils.py
logo_diagram_generator-0.3.5.dist-info/LICENSE
logo_diagram_generator-0.3.5.dist-info/METADATA
logo_diagram_generator-0.3.5.dist-info/WHEEL
logo_diagram_generator-0.3.5.dist-info/entry_points.txt
logo_diagram_generator-0.3.5.dist-info/RECORD
