Metadata-Version: 2.1
Name: logo-diagram-generator
Version: 0.3.5
Summary: Generate SVG diagrams of a (tech) ecosystem, using logos from each tool organised into groups around a central logo
Home-page: https://github.com/beveradb/logo-diagram-generator
License: MIT
Keywords: devops,diagram,diagram-generator,svg,vector-graphics
Author: Andrew Beveridge
Author-email: andrew@beveridge.uk
Requires-Python: >=3.9
Classifier: Development Status :: 4 - Beta
Classifier: Intended Audience :: Developers
Classifier: License :: OSI Approved :: MIT License
Classifier: Operating System :: OS Independent
Classifier: Programming Language :: Python :: 3
Classifier: Programming Language :: Python :: 3.9
Classifier: Programming Language :: Python :: 3.10
Classifier: Programming Language :: Python :: 3.11
Classifier: Programming Language :: Python :: 3.12
Classifier: Topic :: Multimedia :: Graphics
Requires-Dist: cairosvg (>=2)
Requires-Dist: graphviz (>=0.20)
Requires-Dist: pyyaml
Requires-Dist: requests (>=2)
Project-URL: Documentation, https://github.com/beveradb/logo-diagram-generator/blob/main/README.md
Project-URL: Repository, https://github.com/beveradb/logo-diagram-generator
